vistools/__init__.py
vistools/pyvista/__init__.py
vistools/pyvista/camera.py
vistools/pyvista/extrude_shell_surface.py
vistools/pyvista/nonlinear_subdivision.py
vistools/pyvista/polyline_cross_section.py
vistools/pyvista/scalar_bar_to_tikz.py
vistools/pyvista/sort_grid.py
vistools/pyvista/temporal_interpolator.py
vistools/vtk/__init__.py
vistools/vtk/compare_grids.py
vistools/vtk/geometric_search.py
vistools/vtk/merge_polylines.py
vistools/vtk/normal_field.py
vistools/vtk/polyline_cross_section.py
vistools/vtk/utils.py
vistools/vtk/vtk_data_structures_utils.py
vistools-0.4.0.dist-info/licenses/LICENSE
vistools-0.4.0.dist-info/METADATA
vistools-0.4.0.dist-info/WHEEL
vistools-0.4.0.dist-info/top_level.txt
vistools-0.4.0.dist-info/RECORD
