Metadata-Version: 2.4
Name: vistools
Version: 0.4.0
Summary: Utility functionality for vtk and pyvista
Author-email: Ivo Steinbrecher <ivo.steinbrecher@unibw.de>
Project-URL: Repository, https://github.com/isteinbrecher/vistools/
Project-URL: Issues, https://github.com/isteinbrecher/vistools/issues/
Requires-Python: >=3.10
License-File: LICENSE
Requires-Dist: numpy
Requires-Dist: scipy
Requires-Dist: vtk
Provides-Extra: pyvista
Requires-Dist: pyvista; extra == "pyvista"
Requires-Dist: opencv-python; extra == "pyvista"
Provides-Extra: dev
Requires-Dist: pre-commit; extra == "dev"
Requires-Dist: pytest; extra == "dev"
Requires-Dist: pytest-cov; extra == "dev"
Dynamic: license-file
